bmp_to_vid/__init__.py
bmp_to_vid/cli.py
bmp_to_vid-1.0.2.dist-info/METADATA
bmp_to_vid-1.0.2.dist-info/WHEEL
bmp_to_vid-1.0.2.dist-info/entry_points.txt
bmp_to_vid-1.0.2.dist-info/top_level.txt
bmp_to_vid-1.0.2.dist-info/RECORD
